ntrprtr_bitlocker_forensics/Controller.py
ntrprtr_bitlocker_forensics/__init__.py
ntrprtr_bitlocker_forensics/__main__.py
ntrprtr_bitlocker_forensics/config/__init__.py
ntrprtr_bitlocker_forensics/config/bitlocker-metadata-header.json
ntrprtr_bitlocker_forensics/config/bitlocker-volume-header.json
ntrprtr_bitlocker_forensics-0.1.0.dist-info/LICENSE.md
ntrprtr_bitlocker_forensics-0.1.0.dist-info/METADATA
ntrprtr_bitlocker_forensics-0.1.0.dist-info/WHEEL
ntrprtr_bitlocker_forensics-0.1.0.dist-info/entry_points.txt
ntrprtr_bitlocker_forensics-0.1.0.dist-info/top_level.txt
ntrprtr_bitlocker_forensics-0.1.0.dist-info/RECORD
