Metadata-Version: 2.1
Name: ntrprtr-bitlocker-forensics
Version: 0.1.0
Summary: ntrprtr configurations for forensic analysis of bitlocker volumes
Home-page: https://github.com/5f0ne/ntrprtr-bitlocker-forensics
Author: 5f0
License: MIT
Classifier: Operating System :: OS Independent 
Classifier: Programming Language :: Python :: 3 
Classifier: License :: OSI Approved :: MIT License 
License-File: LICENSE.md
